pysoft
