Metadata-Version: 1.0
Name: PySOFT
Version: 0.0.7
Summary: SOFT (Simple Omnibus Format in Text) file parser
Home-page: https://github.com/kpj/PySOFT
Author: kpj
Author-email: kpjkpjkpjkpjkpjkpj@gmail.com
License: MIT
Platform: UNKNOWN
